[
    {
        "id": 1,
        "painterName": "sdfgsdf",
        "title": "dsfgsdfg",
        "fileName": "289710.jpg"
    },
    {
        "id": 2,
        "painterName": "asdfaf",
        "title": "sdfad",
        "fileName": "The-Scream-Edvard-Munch-1612x2048.jpg"
    },
    {
        "id": 3,
        "painterName": "asdfasdf",
        "title": "asdfasdfa",
        "fileName": "hey hey people.jpg"
    },
    {
        "id": 4,
        "painterName": "asdfasdf",
        "title": "asdfasdf",
        "fileName": "placeholder.jpg"
    },
    {
        "id": 5,
        "painterName": "asdfasf",
        "title": "asdfasdf",
        "fileName": "dwarf.jpg"
    },
    {
        "id": 6,
        "painterName": "asdfasdf",
        "title": "asdfasdf",
        "fileName": "elf.png"
    },
    {
        "id": 7,
        "painterName": "asdfsadfasfd",
        "title": "asdfadsf",
        "fileName": "mm.m.00051_20191206.jpg"
    }
]